{
  "video_id": "2025-05-28_13-40-09_UTC",
  "vibes": [
    "Coquette",
    "Clean Girl",
    "Cottagecore"
  ],
  "products": [
    {
      "type": "vest_dress",
      "color": "PINK",
      "matched_product_id": "unknown",
      "match_type": "similar",
      "confidence": 0.6618986276461993
    },
    {
      "type": "vest_dress",
      "color": "Multicolor",
      "matched_product_id": "unknown",
      "match_type": "similar",
      "confidence": 0.6423381004924388
    },
    {
      "type": "vest_dress",
      "color": "Blue",
      "matched_product_id": "unknown",
      "match_type": "similar",
      "confidence": 0.6373890158812944
    },
    {
      "type": "vest_dress",
      "color": "Off White",
      "matched_product_id": "unknown",
      "match_type": "similar",
      "confidence": 0.6354257991142558
    },
    {
      "type": "vest_dress",
      "color": "Tan",
      "matched_product_id": "unknown",
      "match_type": "similar",
      "confidence": 0.6354127554334343
    },
    {
      "type": "vest_dress",
      "color": "PINK",
      "matched_product_id": "unknown",
      "match_type": "similar",
      "confidence": 0.6472127543827394
    },
    {
      "type": "vest_dress",
      "color": "Beige",
      "matched_product_id": "unknown",
      "match_type": "similar",
      "confidence": 0.6340946932282794
    },
    {
      "type": "vest_dress",
      "color": "Green",
      "matched_product_id": "unknown",
      "match_type": "similar",
      "confidence": 0.6283170383215654
    },
    {
      "type": "vest_dress",
      "color": "Multi Colour",
      "matched_product_id": "unknown",
      "match_type": "similar",
      "confidence": 0.6210692848895903
    },
    {
      "type": "vest_dress",
      "color": "Grey",
      "matched_product_id": "unknown",
      "match_type": "similar",
      "confidence": 0.6209236013253256
    },
    {
      "type": "vest",
      "color": "PINK",
      "matched_product_id": "unknown",
      "match_type": "similar",
      "confidence": 0.6530979340773916
    },
    {
      "type": "vest",
      "color": "Tan",
      "matched_product_id": "unknown",
      "match_type": "similar",
      "confidence": 0.6355840023857676
    },
    {
      "type": "vest",
      "color": "Off White",
      "matched_product_id": "unknown",
      "match_type": "similar",
      "confidence": 0.6316327645461342
    },
    {
      "type": "vest",
      "color": "Grey",
      "matched_product_id": "unknown",
      "match_type": "similar",
      "confidence": 0.6312245617650944
    },
    {
      "type": "vest",
      "color": "Black",
      "matched_product_id": "unknown",
      "match_type": "similar",
      "confidence": 0.6261300481155172
    },
    {
      "type": "vest_dress",
      "color": "PINK",
      "matched_product_id": "unknown",
      "match_type": "similar",
      "confidence": 0.6213454620736754
    },
    {
      "type": "vest_dress",
      "color": "Tan",
      "matched_product_id": "unknown",
      "match_type": "similar",
      "confidence": 0.601209010486567
    },
    {
      "type": "skirt",
      "color": "PINK",
      "matched_product_id": "unknown",
      "match_type": "similar",
      "confidence": 0.6472993281206674
    },
    {
      "type": "skirt",
      "color": "Off White",
      "matched_product_id": "unknown",
      "match_type": "similar",
      "confidence": 0.6192196102705497
    },
    {
      "type": "skirt",
      "color": "Khaki",
      "matched_product_id": "unknown",
      "match_type": "similar",
      "confidence": 0.6186257150589931
    },
    {
      "type": "skirt",
      "color": "Green",
      "matched_product_id": "unknown",
      "match_type": "similar",
      "confidence": 0.613218073066056
    },
    {
      "type": "skirt",
      "color": "Maroon",
      "matched_product_id": "unknown",
      "match_type": "similar",
      "confidence": 0.6094723062938712
    },
    {
      "type": "vest_dress",
      "color": "PINK",
      "matched_product_id": "unknown",
      "match_type": "similar",
      "confidence": 0.6358841598242819
    },
    {
      "type": "vest_dress",
      "color": "Off White",
      "matched_product_id": "unknown",
      "match_type": "similar",
      "confidence": 0.6064288437368621
    },
    {
      "type": "vest_dress",
      "color": "Green",
      "matched_product_id": "unknown",
      "match_type": "similar",
      "confidence": 0.605099534472124
    },
    {
      "type": "vest_dress",
      "color": "Beige",
      "matched_product_id": "unknown",
      "match_type": "similar",
      "confidence": 0.6044367253288548
    },
    {
      "type": "vest_dress",
      "color": "Pink",
      "matched_product_id": "unknown",
      "match_type": "similar",
      "confidence": 0.604028827973062
    },
    {
      "type": "vest",
      "color": "Tan",
      "matched_product_id": "unknown",
      "match_type": "similar",
      "confidence": 0.6616385883700285
    },
    {
      "type": "vest",
      "color": "White",
      "matched_product_id": "unknown",
      "match_type": "similar",
      "confidence": 0.658187713252604
    },
    {
      "type": "vest",
      "color": "Black",
      "matched_product_id": "unknown",
      "match_type": "similar",
      "confidence": 0.6561915433538258
    },
    {
      "type": "vest",
      "color": "Green",
      "matched_product_id": "unknown",
      "match_type": "similar",
      "confidence": 0.6514550360083766
    },
    {
      "type": "vest",
      "color": "Black",
      "matched_product_id": "unknown",
      "match_type": "similar",
      "confidence": 0.6499971678976433
    },
    {
      "type": "vest_dress",
      "color": "Multicolor",
      "matched_product_id": "unknown",
      "match_type": "similar",
      "confidence": 0.6179371470580869
    },
    {
      "type": "vest_dress",
      "color": "Olive",
      "matched_product_id": "unknown",
      "match_type": "similar",
      "confidence": 0.6124174331246364
    },
    {
      "type": "vest_dress",
      "color": "PINK",
      "matched_product_id": "unknown",
      "match_type": "similar",
      "confidence": 0.6068740359573572
    },
    {
      "type": "vest_dress",
      "color": "Khaki",
      "matched_product_id": "unknown",
      "match_type": "similar",
      "confidence": 0.604693444878741
    },
    {
      "type": "vest_dress",
      "color": "RED",
      "matched_product_id": "unknown",
      "match_type": "similar",
      "confidence": 0.6044698922780569
    },
    {
      "type": "skirt",
      "color": "PINK",
      "matched_product_id": "unknown",
      "match_type": "similar",
      "confidence": 0.6155779164586729
    },
    {
      "type": "skirt",
      "color": "Off White",
      "matched_product_id": "unknown",
      "match_type": "similar",
      "confidence": 0.6043087302486935
    },
    {
      "type": "skirt",
      "color": "Multicolor",
      "matched_product_id": "unknown",
      "match_type": "similar",
      "confidence": 0.6042399979975376
    },
    {
      "type": "skirt",
      "color": "Maroon",
      "matched_product_id": "unknown",
      "match_type": "similar",
      "confidence": 0.6024146256933766
    },
    {
      "type": "vest_dress",
      "color": "PINK",
      "matched_product_id": "unknown",
      "match_type": "similar",
      "confidence": 0.6259930987546715
    },
    {
      "type": "vest_dress",
      "color": "PINK",
      "matched_product_id": "unknown",
      "match_type": "similar",
      "confidence": 0.618812156357954
    },
    {
      "type": "vest",
      "color": "Pink",
      "matched_product_id": "unknown",
      "match_type": "similar",
      "confidence": 0.6299653581714546
    },
    {
      "type": "vest",
      "color": "Tan",
      "matched_product_id": "unknown",
      "match_type": "similar",
      "confidence": 0.6293918338201863
    },
    {
      "type": "vest",
      "color": "Red",
      "matched_product_id": "unknown",
      "match_type": "similar",
      "confidence": 0.6237662631379334
    },
    {
      "type": "vest",
      "color": "White",
      "matched_product_id": "unknown",
      "match_type": "similar",
      "confidence": 0.6226161081334839
    },
    {
      "type": "vest",
      "color": "Blue",
      "matched_product_id": "unknown",
      "match_type": "similar",
      "confidence": 0.618845527307918
    },
    {
      "type": "vest_dress",
      "color": "Maroon",
      "matched_product_id": "unknown",
      "match_type": "similar",
      "confidence": 0.6753663156923109
    },
    {
      "type": "vest_dress",
      "color": "Off White",
      "matched_product_id": "unknown",
      "match_type": "similar",
      "confidence": 0.6740201964817699
    },
    {
      "type": "vest_dress",
      "color": "Black",
      "matched_product_id": "unknown",
      "match_type": "similar",
      "confidence": 0.6532530547568296
    },
    {
      "type": "vest_dress",
      "color": "Black",
      "matched_product_id": "unknown",
      "match_type": "similar",
      "confidence": 0.6515425713530318
    },
    {
      "type": "vest_dress",
      "color": "Yellow",
      "matched_product_id": "unknown",
      "match_type": "similar",
      "confidence": 0.6499948762761123
    },
    {
      "type": "vest_dress",
      "color": "PINK",
      "matched_product_id": "unknown",
      "match_type": "similar",
      "confidence": 0.6105128026820151
    },
    {
      "type": "vest_dress",
      "color": "PINK",
      "matched_product_id": "unknown",
      "match_type": "similar",
      "confidence": 0.6391096875164518
    },
    {
      "type": "vest_dress",
      "color": "Tan",
      "matched_product_id": "unknown",
      "match_type": "similar",
      "confidence": 0.6184037566853425
    },
    {
      "type": "vest_dress",
      "color": "Off White",
      "matched_product_id": "unknown",
      "match_type": "similar",
      "confidence": 0.6114396899610272
    },
    {
      "type": "vest_dress",
      "color": "Pink",
      "matched_product_id": "unknown",
      "match_type": "similar",
      "confidence": 0.6071580980681786
    },
    {
      "type": "vest_dress",
      "color": "Multicolor",
      "matched_product_id": "unknown",
      "match_type": "similar",
      "confidence": 0.6058995663523893
    },
    {
      "type": "vest",
      "color": "Black",
      "matched_product_id": "unknown",
      "match_type": "similar",
      "confidence": 0.6908130947027625
    },
    {
      "type": "vest",
      "color": "Pink",
      "matched_product_id": "unknown",
      "match_type": "similar",
      "confidence": 0.6887946435728625
    },
    {
      "type": "vest",
      "color": "Green",
      "matched_product_id": "unknown",
      "match_type": "similar",
      "confidence": 0.688609524331764
    },
    {
      "type": "vest",
      "color": "White",
      "matched_product_id": "unknown",
      "match_type": "similar",
      "confidence": 0.6885925525099957
    },
    {
      "type": "vest",
      "color": "Olive",
      "matched_product_id": "unknown",
      "match_type": "similar",
      "confidence": 0.6884863457129945
    },
    {
      "type": "trousers",
      "color": "PINK",
      "matched_product_id": "unknown",
      "match_type": "similar",
      "confidence": 0.6542415281063447
    },
    {
      "type": "trousers",
      "color": "Tan",
      "matched_product_id": "unknown",
      "match_type": "similar",
      "confidence": 0.6512497491418419
    },
    {
      "type": "trousers",
      "color": "Maroon",
      "matched_product_id": "unknown",
      "match_type": "similar",
      "confidence": 0.6485064771538442
    },
    {
      "type": "trousers",
      "color": "Black",
      "matched_product_id": "unknown",
      "match_type": "similar",
      "confidence": 0.648225368255425
    },
    {
      "type": "trousers",
      "color": "Beige",
      "matched_product_id": "unknown",
      "match_type": "similar",
      "confidence": 0.6443026837201974
    },
    {
      "type": "vest",
      "color": "Black",
      "matched_product_id": "unknown",
      "match_type": "similar",
      "confidence": 0.6631868745002297
    },
    {
      "type": "vest",
      "color": "Black",
      "matched_product_id": "unknown",
      "match_type": "similar",
      "confidence": 0.6581936522262818
    },
    {
      "type": "vest",
      "color": "Olive",
      "matched_product_id": "unknown",
      "match_type": "similar",
      "confidence": 0.6561648528337435
    },
    {
      "type": "vest",
      "color": "Black",
      "matched_product_id": "unknown",
      "match_type": "similar",
      "confidence": 0.6541048596476379
    },
    {
      "type": "vest",
      "color": "Green",
      "matched_product_id": "unknown",
      "match_type": "similar",
      "confidence": 0.6500220242154399
    },
    {
      "type": "trousers",
      "color": "PINK",
      "matched_product_id": "unknown",
      "match_type": "similar",
      "confidence": 0.6282099911549232
    },
    {
      "type": "trousers",
      "color": "Multicolor",
      "matched_product_id": "unknown",
      "match_type": "similar",
      "confidence": 0.62321968446924
    },
    {
      "type": "trousers",
      "color": "Black",
      "matched_product_id": "unknown",
      "match_type": "similar",
      "confidence": 0.620984298334531
    },
    {
      "type": "trousers",
      "color": "Tan",
      "matched_product_id": "unknown",
      "match_type": "similar",
      "confidence": 0.6160321694121366
    },
    {
      "type": "trousers",
      "color": "Pink",
      "matched_product_id": "unknown",
      "match_type": "similar",
      "confidence": 0.6104462057983893
    },
    {
      "type": "vest_dress",
      "color": "Tan",
      "matched_product_id": "unknown",
      "match_type": "similar",
      "confidence": 0.6544416853819418
    },
    {
      "type": "vest_dress",
      "color": "PINK",
      "matched_product_id": "unknown",
      "match_type": "similar",
      "confidence": 0.6511798324629829
    },
    {
      "type": "vest_dress",
      "color": "Black",
      "matched_product_id": "unknown",
      "match_type": "similar",
      "confidence": 0.6485725865423675
    },
    {
      "type": "vest_dress",
      "color": "Off White",
      "matched_product_id": "unknown",
      "match_type": "similar",
      "confidence": 0.6392519982988045
    },
    {
      "type": "vest_dress",
      "color": "Green",
      "matched_product_id": "unknown",
      "match_type": "similar",
      "confidence": 0.6383839008022713
    },
    {
      "type": "vest",
      "color": "PINK",
      "matched_product_id": "unknown",
      "match_type": "similar",
      "confidence": 0.6292139011689719
    },
    {
      "type": "vest",
      "color": "Tan",
      "matched_product_id": "unknown",
      "match_type": "similar",
      "confidence": 0.624544208092458
    },
    {
      "type": "vest",
      "color": "Off White",
      "matched_product_id": "unknown",
      "match_type": "similar",
      "confidence": 0.6235171264871289
    },
    {
      "type": "vest",
      "color": "Grey",
      "matched_product_id": "unknown",
      "match_type": "similar",
      "confidence": 0.617955810669352
    },
    {
      "type": "vest",
      "color": "Pink",
      "matched_product_id": "unknown",
      "match_type": "similar",
      "confidence": 0.6174851493733915
    },
    {
      "type": "vest",
      "color": "PINK",
      "matched_product_id": "unknown",
      "match_type": "similar",
      "confidence": 0.6233399750986744
    },
    {
      "type": "skirt",
      "color": "PINK",
      "matched_product_id": "unknown",
      "match_type": "similar",
      "confidence": 0.6321319890575545
    },
    {
      "type": "skirt",
      "color": "Off White",
      "matched_product_id": "unknown",
      "match_type": "similar",
      "confidence": 0.609401929669232
    },
    {
      "type": "vest",
      "color": "Tan",
      "matched_product_id": "unknown",
      "match_type": "similar",
      "confidence": 0.6636028547252151
    },
    {
      "type": "vest",
      "color": "Pink",
      "matched_product_id": "unknown",
      "match_type": "similar",
      "confidence": 0.6538394656738505
    },
    {
      "type": "vest",
      "color": "Black",
      "matched_product_id": "unknown",
      "match_type": "similar",
      "confidence": 0.652205212054348
    },
    {
      "type": "vest",
      "color": "Black",
      "matched_product_id": "unknown",
      "match_type": "similar",
      "confidence": 0.6505690923051313
    },
    {
      "type": "vest",
      "color": "Red",
      "matched_product_id": "unknown",
      "match_type": "similar",
      "confidence": 0.6503756329325171
    },
    {
      "type": "vest_dress",
      "color": "Pink",
      "matched_product_id": "unknown",
      "match_type": "similar",
      "confidence": 0.6660478830533907
    },
    {
      "type": "vest_dress",
      "color": "Off White",
      "matched_product_id": "unknown",
      "match_type": "similar",
      "confidence": 0.6605397410703377
    },
    {
      "type": "vest_dress",
      "color": "Tan",
      "matched_product_id": "unknown",
      "match_type": "similar",
      "confidence": 0.6585114661042878
    },
    {
      "type": "vest_dress",
      "color": "Beige",
      "matched_product_id": "unknown",
      "match_type": "similar",
      "confidence": 0.6570485377441269
    },
    {
      "type": "vest_dress",
      "color": "Green",
      "matched_product_id": "unknown",
      "match_type": "similar",
      "confidence": 0.6561219472409971
    },
    {
      "type": "shorts",
      "color": "Multicolor",
      "matched_product_id": "unknown",
      "match_type": "similar",
      "confidence": 0.6248724720868811
    },
    {
      "type": "shorts",
      "color": "Black",
      "matched_product_id": "unknown",
      "match_type": "similar",
      "confidence": 0.6223089527395133
    },
    {
      "type": "shorts",
      "color": "Tan",
      "matched_product_id": "unknown",
      "match_type": "similar",
      "confidence": 0.6165666386507371
    },
    {
      "type": "shorts",
      "color": "PINK",
      "matched_product_id": "unknown",
      "match_type": "similar",
      "confidence": 0.6121878436830195
    },
    {
      "type": "shorts",
      "color": "Olive",
      "matched_product_id": "unknown",
      "match_type": "similar",
      "confidence": 0.6117655175295712
    },
    {
      "type": "vest",
      "color": "Tan",
      "matched_product_id": "unknown",
      "match_type": "similar",
      "confidence": 0.6804422440458623
    },
    {
      "type": "vest",
      "color": "Pink",
      "matched_product_id": "unknown",
      "match_type": "similar",
      "confidence": 0.6760579634972084
    },
    {
      "type": "vest",
      "color": "Black",
      "matched_product_id": "unknown",
      "match_type": "similar",
      "confidence": 0.6745867907538691
    },
    {
      "type": "vest",
      "color": "Green",
      "matched_product_id": "unknown",
      "match_type": "similar",
      "confidence": 0.6738270326309904
    },
    {
      "type": "vest",
      "color": "Red",
      "matched_product_id": "unknown",
      "match_type": "similar",
      "confidence": 0.6674705756962042
    },
    {
      "type": "vest_dress",
      "color": "PINK",
      "matched_product_id": "unknown",
      "match_type": "similar",
      "confidence": 0.6121518588477791
    },
    {
      "type": "vest_dress",
      "color": "Red",
      "matched_product_id": "unknown",
      "match_type": "similar",
      "confidence": 0.6091643543264128
    },
    {
      "type": "vest_dress",
      "color": "Tan",
      "matched_product_id": "unknown",
      "match_type": "similar",
      "confidence": 0.602989296134341
    },
    {
      "type": "vest_dress",
      "color": "Green",
      "matched_product_id": "unknown",
      "match_type": "similar",
      "confidence": 0.601795801264813
    },
    {
      "type": "vest_dress",
      "color": "Black",
      "matched_product_id": "unknown",
      "match_type": "similar",
      "confidence": 0.6003127726321299
    },
    {
      "type": "skirt",
      "color": "PINK",
      "matched_product_id": "unknown",
      "match_type": "similar",
      "confidence": 0.6494103861590547
    },
    {
      "type": "skirt",
      "color": "Tan",
      "matched_product_id": "unknown",
      "match_type": "similar",
      "confidence": 0.6352134847532742
    },
    {
      "type": "skirt",
      "color": "Off White",
      "matched_product_id": "unknown",
      "match_type": "similar",
      "confidence": 0.6292545868944501
    },
    {
      "type": "skirt",
      "color": "Black",
      "matched_product_id": "unknown",
      "match_type": "similar",
      "confidence": 0.6249938207358113
    },
    {
      "type": "skirt",
      "color": "Green",
      "matched_product_id": "unknown",
      "match_type": "similar",
      "confidence": 0.6243800195011574
    },
    {
      "type": "vest_dress",
      "color": "PINK",
      "matched_product_id": "unknown",
      "match_type": "similar",
      "confidence": 0.6028664191773231
    },
    {
      "type": "vest_dress",
      "color": "Black",
      "matched_product_id": "unknown",
      "match_type": "similar",
      "confidence": 0.6021646782363682
    },
    {
      "type": "vest_dress",
      "color": "PINK",
      "matched_product_id": "unknown",
      "match_type": "similar",
      "confidence": 0.6487851203549158
    },
    {
      "type": "vest_dress",
      "color": "Green",
      "matched_product_id": "unknown",
      "match_type": "similar",
      "confidence": 0.6246326835169499
    },
    {
      "type": "vest_dress",
      "color": "Khaki",
      "matched_product_id": "unknown",
      "match_type": "similar",
      "confidence": 0.624438070661942
    },
    {
      "type": "vest_dress",
      "color": "Tan",
      "matched_product_id": "unknown",
      "match_type": "similar",
      "confidence": 0.6201712873521138
    },
    {
      "type": "vest_dress",
      "color": "Navy Blue",
      "matched_product_id": "unknown",
      "match_type": "similar",
      "confidence": 0.6189131704443604
    },
    {
      "type": "vest_dress",
      "color": "PINK",
      "matched_product_id": "unknown",
      "match_type": "similar",
      "confidence": 0.6334473249475356
    },
    {
      "type": "vest_dress",
      "color": "Tan",
      "matched_product_id": "unknown",
      "match_type": "similar",
      "confidence": 0.6212623093670945
    },
    {
      "type": "vest_dress",
      "color": "Green",
      "matched_product_id": "unknown",
      "match_type": "similar",
      "confidence": 0.613843150148192
    },
    {
      "type": "vest_dress",
      "color": "Off White",
      "matched_product_id": "unknown",
      "match_type": "similar",
      "confidence": 0.6131771038955048
    },
    {
      "type": "vest_dress",
      "color": "Grey",
      "matched_product_id": "unknown",
      "match_type": "similar",
      "confidence": 0.6084886206984222
    },
    {
      "type": "vest",
      "color": "Pink",
      "matched_product_id": "unknown",
      "match_type": "similar",
      "confidence": 0.6771096752811152
    },
    {
      "type": "vest",
      "color": "Black",
      "matched_product_id": "unknown",
      "match_type": "similar",
      "confidence": 0.6727414176600789
    },
    {
      "type": "vest",
      "color": "Navy",
      "matched_product_id": "unknown",
      "match_type": "similar",
      "confidence": 0.6660739028005949
    },
    {
      "type": "vest",
      "color": "Yellow",
      "matched_product_id": "unknown",
      "match_type": "similar",
      "confidence": 0.665025048016196
    },
    {
      "type": "vest",
      "color": "Off White",
      "matched_product_id": "unknown",
      "match_type": "similar",
      "confidence": 0.663625297543728
    },
    {
      "type": "skirt",
      "color": "PINK",
      "matched_product_id": "unknown",
      "match_type": "similar",
      "confidence": 0.6436784431538387
    },
    {
      "type": "skirt",
      "color": "Multicolor",
      "matched_product_id": "unknown",
      "match_type": "similar",
      "confidence": 0.6350390721712973
    },
    {
      "type": "skirt",
      "color": "Off White",
      "matched_product_id": "unknown",
      "match_type": "similar",
      "confidence": 0.6287505403167555
    },
    {
      "type": "skirt",
      "color": "Black",
      "matched_product_id": "unknown",
      "match_type": "similar",
      "confidence": 0.6246013131462048
    },
    {
      "type": "skirt",
      "color": "Black",
      "matched_product_id": "unknown",
      "match_type": "similar",
      "confidence": 0.6221258199805314
    },
    {
      "type": "vest_dress",
      "color": "Beige",
      "matched_product_id": "unknown",
      "match_type": "similar",
      "confidence": 0.6525661248055833
    },
    {
      "type": "vest_dress",
      "color": "PINK",
      "matched_product_id": "unknown",
      "match_type": "similar",
      "confidence": 0.6519832868721395
    },
    {
      "type": "vest_dress",
      "color": "Pink",
      "matched_product_id": "unknown",
      "match_type": "similar",
      "confidence": 0.6510151604217369
    },
    {
      "type": "vest_dress",
      "color": "Black",
      "matched_product_id": "unknown",
      "match_type": "similar",
      "confidence": 0.6474195009797801
    },
    {
      "type": "vest_dress",
      "color": "Navy",
      "matched_product_id": "unknown",
      "match_type": "similar",
      "confidence": 0.6464725429571948
    },
    {
      "type": "vest_dress",
      "color": "Tan",
      "matched_product_id": "unknown",
      "match_type": "similar",
      "confidence": 0.614064498305479
    },
    {
      "type": "vest_dress",
      "color": "PINK",
      "matched_product_id": "unknown",
      "match_type": "similar",
      "confidence": 0.6069534033867036
    },
    {
      "type": "vest_dress",
      "color": "Olive",
      "matched_product_id": "unknown",
      "match_type": "similar",
      "confidence": 0.6054176331921493
    },
    {
      "type": "vest_dress",
      "color": "Pink",
      "matched_product_id": "unknown",
      "match_type": "similar",
      "confidence": 0.6052427554255146
    },
    {
      "type": "vest",
      "color": "PINK",
      "matched_product_id": "unknown",
      "match_type": "similar",
      "confidence": 0.6384431032631226
    },
    {
      "type": "vest",
      "color": "Tan",
      "matched_product_id": "unknown",
      "match_type": "similar",
      "confidence": 0.6364099973765542
    },
    {
      "type": "vest",
      "color": "Off White",
      "matched_product_id": "unknown",
      "match_type": "similar",
      "confidence": 0.6359471180219566
    },
    {
      "type": "vest",
      "color": "Grey",
      "matched_product_id": "unknown",
      "match_type": "similar",
      "confidence": 0.6299754351419408
    },
    {
      "type": "vest",
      "color": "Maroon",
      "matched_product_id": "unknown",
      "match_type": "similar",
      "confidence": 0.6239173674350714
    },
    {
      "type": "shorts",
      "color": "Black",
      "matched_product_id": "unknown",
      "match_type": "similar",
      "confidence": 0.626419492839356
    },
    {
      "type": "shorts",
      "color": "Tan",
      "matched_product_id": "unknown",
      "match_type": "similar",
      "confidence": 0.6262207031341127
    },
    {
      "type": "shorts",
      "color": "Black",
      "matched_product_id": "unknown",
      "match_type": "similar",
      "confidence": 0.6252720785528699
    },
    {
      "type": "shorts",
      "color": "Green",
      "matched_product_id": "unknown",
      "match_type": "similar",
      "confidence": 0.6240348636726224
    },
    {
      "type": "shorts",
      "color": "Pink",
      "matched_product_id": "unknown",
      "match_type": "similar",
      "confidence": 0.6217701546533747
    },
    {
      "type": "vest_dress",
      "color": "Black",
      "matched_product_id": "unknown",
      "match_type": "similar",
      "confidence": 0.6877328054921175
    },
    {
      "type": "vest_dress",
      "color": "Tan",
      "matched_product_id": "unknown",
      "match_type": "similar",
      "confidence": 0.6805219260554728
    },
    {
      "type": "vest_dress",
      "color": "Green",
      "matched_product_id": "unknown",
      "match_type": "similar",
      "confidence": 0.6675874641922942
    },
    {
      "type": "vest_dress",
      "color": "White",
      "matched_product_id": "unknown",
      "match_type": "similar",
      "confidence": 0.6632094989257228
    },
    {
      "type": "vest_dress",
      "color": "Multi",
      "matched_product_id": "unknown",
      "match_type": "similar",
      "confidence": 0.6631808975053818
    },
    {
      "type": "vest",
      "color": "Olive",
      "matched_product_id": "unknown",
      "match_type": "similar",
      "confidence": 0.6336023908976939
    },
    {
      "type": "vest",
      "color": "Beige",
      "matched_product_id": "unknown",
      "match_type": "similar",
      "confidence": 0.62572066319942
    },
    {
      "type": "vest",
      "color": "Black",
      "matched_product_id": "unknown",
      "match_type": "similar",
      "confidence": 0.6228890377767294
    },
    {
      "type": "vest",
      "color": "Blue",
      "matched_product_id": "unknown",
      "match_type": "similar",
      "confidence": 0.62125011673516
    },
    {
      "type": "vest",
      "color": "Tan",
      "matched_product_id": "unknown",
      "match_type": "similar",
      "confidence": 0.6206224063074578
    },
    {
      "type": "vest_dress",
      "color": "Off White",
      "matched_product_id": "unknown",
      "match_type": "similar",
      "confidence": 0.6482554244181077
    },
    {
      "type": "vest_dress",
      "color": "Olive",
      "matched_product_id": "unknown",
      "match_type": "similar",
      "confidence": 0.6415247420904521
    },
    {
      "type": "vest_dress",
      "color": "PINK",
      "matched_product_id": "unknown",
      "match_type": "similar",
      "confidence": 0.6413885039367069
    },
    {
      "type": "vest_dress",
      "color": "Black",
      "matched_product_id": "unknown",
      "match_type": "similar",
      "confidence": 0.6404789225708096
    },
    {
      "type": "vest_dress",
      "color": "Olive",
      "matched_product_id": "unknown",
      "match_type": "similar",
      "confidence": 0.6395648956165914
    },
    {
      "type": "vest_dress",
      "color": "PINK",
      "matched_product_id": "unknown",
      "match_type": "similar",
      "confidence": 0.647899988422369
    },
    {
      "type": "vest_dress",
      "color": "Pink",
      "matched_product_id": "unknown",
      "match_type": "similar",
      "confidence": 0.6291787419902344
    },
    {
      "type": "vest_dress",
      "color": "Tan",
      "matched_product_id": "unknown",
      "match_type": "similar",
      "confidence": 0.6249395536982558
    },
    {
      "type": "vest_dress",
      "color": "Green",
      "matched_product_id": "unknown",
      "match_type": "similar",
      "confidence": 0.6233843056243313
    },
    {
      "type": "vest_dress",
      "color": "White",
      "matched_product_id": "unknown",
      "match_type": "similar",
      "confidence": 0.621594086540403
    },
    {
      "type": "vest",
      "color": "Tan",
      "matched_product_id": "unknown",
      "match_type": "similar",
      "confidence": 0.6705109143859468
    },
    {
      "type": "vest",
      "color": "Red",
      "matched_product_id": "unknown",
      "match_type": "similar",
      "confidence": 0.6673012118200247
    },
    {
      "type": "vest",
      "color": "Olive",
      "matched_product_id": "unknown",
      "match_type": "similar",
      "confidence": 0.6658951373729896
    },
    {
      "type": "vest",
      "color": "Pink",
      "matched_product_id": "unknown",
      "match_type": "similar",
      "confidence": 0.6618863545858307
    },
    {
      "type": "vest",
      "color": "Black",
      "matched_product_id": "unknown",
      "match_type": "similar",
      "confidence": 0.6602806382879916
    },
    {
      "type": "vest_dress",
      "color": "Black",
      "matched_product_id": "unknown",
      "match_type": "similar",
      "confidence": 0.6302236763764014
    },
    {
      "type": "vest_dress",
      "color": "PINK",
      "matched_product_id": "unknown",
      "match_type": "similar",
      "confidence": 0.6263394894777291
    },
    {
      "type": "vest_dress",
      "color": "Tan",
      "matched_product_id": "unknown",
      "match_type": "similar",
      "confidence": 0.6238924721762117
    },
    {
      "type": "vest_dress",
      "color": "Pink",
      "matched_product_id": "unknown",
      "match_type": "similar",
      "confidence": 0.6232274168687292
    },
    {
      "type": "vest_dress",
      "color": "White",
      "matched_product_id": "unknown",
      "match_type": "similar",
      "confidence": 0.6228743993304511
    },
    {
      "type": "vest",
      "color": "Olive",
      "matched_product_id": "unknown",
      "match_type": "similar",
      "confidence": 0.6412566863918308
    },
    {
      "type": "vest",
      "color": "Blue",
      "matched_product_id": "unknown",
      "match_type": "similar",
      "confidence": 0.6374273993901034
    },
    {
      "type": "vest",
      "color": "Off White",
      "matched_product_id": "unknown",
      "match_type": "similar",
      "confidence": 0.6366965102216804
    },
    {
      "type": "vest",
      "color": "Black",
      "matched_product_id": "unknown",
      "match_type": "similar",
      "confidence": 0.6364670716654897
    },
    {
      "type": "vest",
      "color": "Black",
      "matched_product_id": "unknown",
      "match_type": "similar",
      "confidence": 0.6353842152248171
    },
    {
      "type": "vest",
      "color": "PINK",
      "matched_product_id": "unknown",
      "match_type": "similar",
      "confidence": 0.621116719201326
    },
    {
      "type": "vest",
      "color": "Grey",
      "matched_product_id": "unknown",
      "match_type": "similar",
      "confidence": 0.6186647007712208
    },
    {
      "type": "vest",
      "color": "Pink",
      "matched_product_id": "unknown",
      "match_type": "similar",
      "confidence": 0.6172373251558995
    },
    {
      "type": "vest",
      "color": "Black",
      "matched_product_id": "unknown",
      "match_type": "similar",
      "confidence": 0.6153996036726452
    },
    {
      "type": "vest",
      "color": "Green",
      "matched_product_id": "unknown",
      "match_type": "similar",
      "confidence": 0.6125692166553881
    },
    {
      "type": "skirt",
      "color": "Off White",
      "matched_product_id": "unknown",
      "match_type": "similar",
      "confidence": 0.6415613682621915
    },
    {
      "type": "skirt",
      "color": "Maroon",
      "matched_product_id": "unknown",
      "match_type": "similar",
      "confidence": 0.6281240034177413
    },
    {
      "type": "skirt",
      "color": "Multicolor",
      "matched_product_id": "unknown",
      "match_type": "similar",
      "confidence": 0.6257022976856064
    },
    {
      "type": "skirt",
      "color": "Black",
      "matched_product_id": "unknown",
      "match_type": "similar",
      "confidence": 0.624627939389122
    },
    {
      "type": "skirt",
      "color": "PINK",
      "matched_product_id": "unknown",
      "match_type": "similar",
      "confidence": 0.6234957388069239
    },
    {
      "type": "trousers",
      "color": "Off White",
      "matched_product_id": "unknown",
      "match_type": "similar",
      "confidence": 0.6407993858916256
    },
    {
      "type": "trousers",
      "color": "Maroon",
      "matched_product_id": "unknown",
      "match_type": "similar",
      "confidence": 0.6277835999380494
    },
    {
      "type": "trousers",
      "color": "Multicolor",
      "matched_product_id": "unknown",
      "match_type": "similar",
      "confidence": 0.6255555989730536
    },
    {
      "type": "trousers",
      "color": "Black",
      "matched_product_id": "unknown",
      "match_type": "similar",
      "confidence": 0.6249352006376738
    },
    {
      "type": "trousers",
      "color": "PINK",
      "matched_product_id": "unknown",
      "match_type": "similar",
      "confidence": 0.6227447415271411
    },
    {
      "type": "vest_dress",
      "color": "PINK",
      "matched_product_id": "unknown",
      "match_type": "similar",
      "confidence": 0.634177481224778
    },
    {
      "type": "vest_dress",
      "color": "Pink",
      "matched_product_id": "unknown",
      "match_type": "similar",
      "confidence": 0.6099961583498662
    },
    {
      "type": "vest_dress",
      "color": "Off White",
      "matched_product_id": "unknown",
      "match_type": "similar",
      "confidence": 0.6030636836684319
    },
    {
      "type": "vest_dress",
      "color": "Maroon",
      "matched_product_id": "unknown",
      "match_type": "similar",
      "confidence": 0.6012730683200047
    },
    {
      "type": "vest_dress",
      "color": "Grey",
      "matched_product_id": "unknown",
      "match_type": "similar",
      "confidence": 0.6003257898241992
    },
    {
      "type": "vest",
      "color": "PINK",
      "matched_product_id": "unknown",
      "match_type": "similar",
      "confidence": 0.6178883538696837
    },
    {
      "type": "vest",
      "color": "Black",
      "matched_product_id": "unknown",
      "match_type": "similar",
      "confidence": 0.6079471075070155
    },
    {
      "type": "vest",
      "color": "Green",
      "matched_product_id": "unknown",
      "match_type": "similar",
      "confidence": 0.603863532270038
    },
    {
      "type": "vest",
      "color": "PINK",
      "matched_product_id": "unknown",
      "match_type": "similar",
      "confidence": 0.6278033564239656
    },
    {
      "type": "vest",
      "color": "Pink",
      "matched_product_id": "unknown",
      "match_type": "similar",
      "confidence": 0.6149156524128192
    },
    {
      "type": "vest",
      "color": "Off White",
      "matched_product_id": "unknown",
      "match_type": "similar",
      "confidence": 0.608994224702291
    },
    {
      "type": "vest",
      "color": "Pink",
      "matched_product_id": "unknown",
      "match_type": "similar",
      "confidence": 0.6052733905011146
    },
    {
      "type": "vest",
      "color": "Green",
      "matched_product_id": "unknown",
      "match_type": "similar",
      "confidence": 0.6051779363268809
    },
    {
      "type": "skirt",
      "color": "PINK",
      "matched_product_id": "unknown",
      "match_type": "similar",
      "confidence": 0.6059885504783011
    },
    {
      "type": "vest",
      "color": "PINK",
      "matched_product_id": "unknown",
      "match_type": "similar",
      "confidence": 0.6489623466659075
    },
    {
      "type": "vest",
      "color": "Pink",
      "matched_product_id": "unknown",
      "match_type": "similar",
      "confidence": 0.6358943306336567
    },
    {
      "type": "vest",
      "color": "Off White",
      "matched_product_id": "unknown",
      "match_type": "similar",
      "confidence": 0.6247403062048272
    },
    {
      "type": "vest",
      "color": "Tan",
      "matched_product_id": "unknown",
      "match_type": "similar",
      "confidence": 0.6206338396272028
    },
    {
      "type": "vest",
      "color": "Black",
      "matched_product_id": "unknown",
      "match_type": "similar",
      "confidence": 0.6202581382276839
    },
    {
      "type": "skirt",
      "color": "PINK",
      "matched_product_id": "unknown",
      "match_type": "similar",
      "confidence": 0.6344180581559163
    },
    {
      "type": "skirt",
      "color": "Blue",
      "matched_product_id": "unknown",
      "match_type": "similar",
      "confidence": 0.6093800163920642
    },
    {
      "type": "skirt",
      "color": "White",
      "matched_product_id": "unknown",
      "match_type": "similar",
      "confidence": 0.6027689506095462
    },
    {
      "type": "vest_dress",
      "color": "PINK",
      "matched_product_id": "unknown",
      "match_type": "similar",
      "confidence": 0.6742982728066287
    },
    {
      "type": "vest_dress",
      "color": "Multicolor",
      "matched_product_id": "unknown",
      "match_type": "similar",
      "confidence": 0.6704832472663782
    },
    {
      "type": "vest_dress",
      "color": "Black",
      "matched_product_id": "unknown",
      "match_type": "similar",
      "confidence": 0.6658819227986986
    },
    {
      "type": "vest_dress",
      "color": "Tan",
      "matched_product_id": "unknown",
      "match_type": "similar",
      "confidence": 0.6658168090367366
    },
    {
      "type": "vest_dress",
      "color": "Black",
      "matched_product_id": "unknown",
      "match_type": "similar",
      "confidence": 0.658854683629924
    },
    {
      "type": "vest_dress",
      "color": "PINK",
      "matched_product_id": "unknown",
      "match_type": "similar",
      "confidence": 0.6104501372321688
    },
    {
      "type": "vest_dress",
      "color": "Black",
      "matched_product_id": "unknown",
      "match_type": "similar",
      "confidence": 0.610068846312011
    },
    {
      "type": "vest_dress",
      "color": "Off White",
      "matched_product_id": "unknown",
      "match_type": "similar",
      "confidence": 0.6094556127897938
    },
    {
      "type": "vest_dress",
      "color": "Black",
      "matched_product_id": "unknown",
      "match_type": "similar",
      "confidence": 0.6094133738959542
    },
    {
      "type": "vest_dress",
      "color": "Multicolor",
      "matched_product_id": "unknown",
      "match_type": "similar",
      "confidence": 0.6055595840652929
    },
    {
      "type": "vest",
      "color": "Off White",
      "matched_product_id": "unknown",
      "match_type": "similar",
      "confidence": 0.6185625818588478
    },
    {
      "type": "vest",
      "color": "Pink",
      "matched_product_id": "unknown",
      "match_type": "similar",
      "confidence": 0.6156470836512228
    },
    {
      "type": "vest",
      "color": "Pink",
      "matched_product_id": "unknown",
      "match_type": "similar",
      "confidence": 0.6139957985910374
    },
    {
      "type": "vest",
      "color": "Off White",
      "matched_product_id": "unknown",
      "match_type": "similar",
      "confidence": 0.6135692248727674
    },
    {
      "type": "vest",
      "color": "Tan",
      "matched_product_id": "unknown",
      "match_type": "similar",
      "confidence": 0.6092539903135056
    },
    {
      "type": "skirt",
      "color": "PINK",
      "matched_product_id": "unknown",
      "match_type": "similar",
      "confidence": 0.6784974522196655
    },
    {
      "type": "skirt",
      "color": "Maroon",
      "matched_product_id": "unknown",
      "match_type": "similar",
      "confidence": 0.6387124101247614
    },
    {
      "type": "skirt",
      "color": "Multicolor",
      "matched_product_id": "unknown",
      "match_type": "similar",
      "confidence": 0.6317825180793968
    },
    {
      "type": "skirt",
      "color": "Black",
      "matched_product_id": "unknown",
      "match_type": "similar",
      "confidence": 0.6285174439535767
    },
    {
      "type": "skirt",
      "color": "Off White",
      "matched_product_id": "unknown",
      "match_type": "similar",
      "confidence": 0.6270177681773575
    },
    {
      "type": "vest_dress",
      "color": "PINK",
      "matched_product_id": "unknown",
      "match_type": "similar",
      "confidence": 0.6299875232008496
    },
    {
      "type": "vest_dress",
      "color": "Off White",
      "matched_product_id": "unknown",
      "match_type": "similar",
      "confidence": 0.6088288076504231
    },
    {
      "type": "vest",
      "color": "Off White",
      "matched_product_id": "unknown",
      "match_type": "similar",
      "confidence": 0.6214749982237979
    },
    {
      "type": "vest",
      "color": "PINK",
      "matched_product_id": "unknown",
      "match_type": "similar",
      "confidence": 0.6213951020088578
    },
    {
      "type": "vest",
      "color": "Off White",
      "matched_product_id": "unknown",
      "match_type": "similar",
      "confidence": 0.6173964377453298
    },
    {
      "type": "vest",
      "color": "Pink",
      "matched_product_id": "unknown",
      "match_type": "similar",
      "confidence": 0.6164668873504218
    },
    {
      "type": "vest",
      "color": "Tan",
      "matched_product_id": "unknown",
      "match_type": "similar",
      "confidence": 0.6120333018875496
    },
    {
      "type": "vest_dress",
      "color": "PINK",
      "matched_product_id": "unknown",
      "match_type": "similar",
      "confidence": 0.6199617348447045
    },
    {
      "type": "skirt",
      "color": "PINK",
      "matched_product_id": "unknown",
      "match_type": "similar",
      "confidence": 0.6777727261819704
    },
    {
      "type": "skirt",
      "color": "Maroon",
      "matched_product_id": "unknown",
      "match_type": "similar",
      "confidence": 0.6352156492827857
    },
    {
      "type": "skirt",
      "color": "Multicolor",
      "matched_product_id": "unknown",
      "match_type": "similar",
      "confidence": 0.6343656921966614
    },
    {
      "type": "skirt",
      "color": "Black",
      "matched_product_id": "unknown",
      "match_type": "similar",
      "confidence": 0.6322462859447661
    },
    {
      "type": "skirt",
      "color": "Off White",
      "matched_product_id": "unknown",
      "match_type": "similar",
      "confidence": 0.6287083883279019
    },
    {
      "type": "vest_dress",
      "color": "PINK",
      "matched_product_id": "unknown",
      "match_type": "similar",
      "confidence": 0.6471098049855163
    },
    {
      "type": "vest_dress",
      "color": "Tan",
      "matched_product_id": "unknown",
      "match_type": "similar",
      "confidence": 0.6304899543239829
    },
    {
      "type": "vest_dress",
      "color": "Multicolor",
      "matched_product_id": "unknown",
      "match_type": "similar",
      "confidence": 0.62385493583119
    },
    {
      "type": "vest_dress",
      "color": "Off White",
      "matched_product_id": "unknown",
      "match_type": "similar",
      "confidence": 0.6223841431456938
    },
    {
      "type": "vest_dress",
      "color": "Maroon",
      "matched_product_id": "unknown",
      "match_type": "similar",
      "confidence": 0.6205533102691836
    },
    {
      "type": "skirt",
      "color": "Off White",
      "matched_product_id": "unknown",
      "match_type": "similar",
      "confidence": 0.6501366850508657
    },
    {
      "type": "skirt",
      "color": "PINK",
      "matched_product_id": "unknown",
      "match_type": "similar",
      "confidence": 0.6459362443685842
    },
    {
      "type": "skirt",
      "color": "Multicolor",
      "matched_product_id": "unknown",
      "match_type": "similar",
      "confidence": 0.6412323488515909
    },
    {
      "type": "skirt",
      "color": "Maroon",
      "matched_product_id": "unknown",
      "match_type": "similar",
      "confidence": 0.6364583553440437
    },
    {
      "type": "skirt",
      "color": "Black",
      "matched_product_id": "unknown",
      "match_type": "similar",
      "confidence": 0.6332316459262729
    },
    {
      "type": "vest_dress",
      "color": "PINK",
      "matched_product_id": "unknown",
      "match_type": "similar",
      "confidence": 0.6172633726656913
    },
    {
      "type": "vest",
      "color": "PINK",
      "matched_product_id": "unknown",
      "match_type": "similar",
      "confidence": 0.6145299349731893
    },
    {
      "type": "skirt",
      "color": "PINK",
      "matched_product_id": "unknown",
      "match_type": "similar",
      "confidence": 0.6412548726544304
    },
    {
      "type": "skirt",
      "color": "Off White",
      "matched_product_id": "unknown",
      "match_type": "similar",
      "confidence": 0.6262085254634451
    },
    {
      "type": "skirt",
      "color": "Multicolor",
      "matched_product_id": "unknown",
      "match_type": "similar",
      "confidence": 0.6247539855715228
    },
    {
      "type": "skirt",
      "color": "Black",
      "matched_product_id": "unknown",
      "match_type": "similar",
      "confidence": 0.618584362269192
    },
    {
      "type": "skirt",
      "color": "Maroon",
      "matched_product_id": "unknown",
      "match_type": "similar",
      "confidence": 0.6151058399582451
    },
    {
      "type": "vest_dress",
      "color": "PINK",
      "matched_product_id": "unknown",
      "match_type": "similar",
      "confidence": 0.6273110601700856
    },
    {
      "type": "vest",
      "color": "PINK",
      "matched_product_id": "unknown",
      "match_type": "similar",
      "confidence": 0.6360941976004577
    },
    {
      "type": "vest",
      "color": "Off White",
      "matched_product_id": "unknown",
      "match_type": "similar",
      "confidence": 0.6012893165736204
    },
    {
      "type": "vest_dress",
      "color": "PINK",
      "matched_product_id": "unknown",
      "match_type": "similar",
      "confidence": 0.627030867857179
    },
    {
      "type": "vest_dress",
      "color": "Off White",
      "matched_product_id": "unknown",
      "match_type": "similar",
      "confidence": 0.6037873610437826
    },
    {
      "type": "vest_dress",
      "color": "Tan",
      "matched_product_id": "unknown",
      "match_type": "similar",
      "confidence": 0.6033883685109342
    },
    {
      "type": "skirt",
      "color": "Off White",
      "matched_product_id": "unknown",
      "match_type": "similar",
      "confidence": 0.6527841291260964
    },
    {
      "type": "skirt",
      "color": "Olive",
      "matched_product_id": "unknown",
      "match_type": "similar",
      "confidence": 0.647906919176033
    },
    {
      "type": "skirt",
      "color": "Maroon",
      "matched_product_id": "unknown",
      "match_type": "similar",
      "confidence": 0.647367289870725
    },
    {
      "type": "skirt",
      "color": "Multicolor",
      "matched_product_id": "unknown",
      "match_type": "similar",
      "confidence": 0.6470490841945534
    },
    {
      "type": "skirt",
      "color": "Yellow",
      "matched_product_id": "unknown",
      "match_type": "similar",
      "confidence": 0.6449865750946429
    },
    {
      "type": "vest",
      "color": "Pink",
      "matched_product_id": "unknown",
      "match_type": "similar",
      "confidence": 0.6394438918363158
    },
    {
      "type": "vest",
      "color": "PINK",
      "matched_product_id": "unknown",
      "match_type": "similar",
      "confidence": 0.6322012340294655
    },
    {
      "type": "vest",
      "color": "Black",
      "matched_product_id": "unknown",
      "match_type": "similar",
      "confidence": 0.6319919971563929
    },
    {
      "type": "vest",
      "color": "Tan",
      "matched_product_id": "unknown",
      "match_type": "similar",
      "confidence": 0.6298120671294364
    },
    {
      "type": "vest",
      "color": "Blue",
      "matched_product_id": "unknown",
      "match_type": "similar",
      "confidence": 0.6296312503241562
    },
    {
      "type": "skirt",
      "color": "PINK",
      "matched_product_id": "unknown",
      "match_type": "similar",
      "confidence": 0.6410370292028211
    },
    {
      "type": "skirt",
      "color": "Off White",
      "matched_product_id": "unknown",
      "match_type": "similar",
      "confidence": 0.6193805926787181
    },
    {
      "type": "skirt",
      "color": "Grey",
      "matched_product_id": "unknown",
      "match_type": "similar",
      "confidence": 0.6159723687245295
    },
    {
      "type": "skirt",
      "color": "Navy",
      "matched_product_id": "unknown",
      "match_type": "similar",
      "confidence": 0.6103340591014181
    },
    {
      "type": "skirt",
      "color": "Multicolor",
      "matched_product_id": "unknown",
      "match_type": "similar",
      "confidence": 0.6096828912108168
    },
    {
      "type": "vest",
      "color": "PINK",
      "matched_product_id": "unknown",
      "match_type": "similar",
      "confidence": 0.6413842129458394
    },
    {
      "type": "vest",
      "color": "Pink",
      "matched_product_id": "unknown",
      "match_type": "similar",
      "confidence": 0.6299104845536314
    },
    {
      "type": "vest",
      "color": "Tan",
      "matched_product_id": "unknown",
      "match_type": "similar",
      "confidence": 0.6223144234579806
    },
    {
      "type": "vest",
      "color": "Black",
      "matched_product_id": "unknown",
      "match_type": "similar",
      "confidence": 0.6209425147207782
    },
    {
      "type": "vest",
      "color": "Green",
      "matched_product_id": "unknown",
      "match_type": "similar",
      "confidence": 0.6187948788329141
    },
    {
      "type": "skirt",
      "color": "PINK",
      "matched_product_id": "unknown",
      "match_type": "similar",
      "confidence": 0.6320326619967349
    },
    {
      "type": "skirt",
      "color": "Off White",
      "matched_product_id": "unknown",
      "match_type": "similar",
      "confidence": 0.6120660573373415
    },
    {
      "type": "skirt",
      "color": "Grey",
      "matched_product_id": "unknown",
      "match_type": "similar",
      "confidence": 0.6115769215122556
    },
    {
      "type": "skirt",
      "color": "Maroon",
      "matched_product_id": "unknown",
      "match_type": "similar",
      "confidence": 0.607185345455314
    },
    {
      "type": "skirt",
      "color": "White",
      "matched_product_id": "unknown",
      "match_type": "similar",
      "confidence": 0.6049920268796621
    },
    {
      "type": "vest",
      "color": "Pink",
      "matched_product_id": "unknown",
      "match_type": "similar",
      "confidence": 0.6620745218677514
    },
    {
      "type": "vest",
      "color": "PINK",
      "matched_product_id": "unknown",
      "match_type": "similar",
      "confidence": 0.6595385891740357
    },
    {
      "type": "vest",
      "color": "Green",
      "matched_product_id": "unknown",
      "match_type": "similar",
      "confidence": 0.6565120761135674
    },
    {
      "type": "vest",
      "color": "Black",
      "matched_product_id": "unknown",
      "match_type": "similar",
      "confidence": 0.6563297014960815
    },
    {
      "type": "vest",
      "color": "Tan",
      "matched_product_id": "unknown",
      "match_type": "similar",
      "confidence": 0.6532676551516989
    },
    {
      "type": "skirt",
      "color": "PINK",
      "matched_product_id": "unknown",
      "match_type": "similar",
      "confidence": 0.6152794921627597
    },
    {
      "type": "skirt",
      "color": "Off White",
      "matched_product_id": "unknown",
      "match_type": "similar",
      "confidence": 0.6088734404056597
    },
    {
      "type": "skirt",
      "color": "Maroon",
      "matched_product_id": "unknown",
      "match_type": "similar",
      "confidence": 0.6032649384177518
    },
    {
      "type": "vest_dress",
      "color": "Pink",
      "matched_product_id": "unknown",
      "match_type": "similar",
      "confidence": 0.617358952020085
    },
    {
      "type": "vest_dress",
      "color": "Grey",
      "matched_product_id": "unknown",
      "match_type": "similar",
      "confidence": 0.6143609799782858
    },
    {
      "type": "vest_dress",
      "color": "Black",
      "matched_product_id": "unknown",
      "match_type": "similar",
      "confidence": 0.614182022361839
    },
    {
      "type": "vest_dress",
      "color": "PINK",
      "matched_product_id": "unknown",
      "match_type": "similar",
      "confidence": 0.6139936639099706
    },
    {
      "type": "vest_dress",
      "color": "Off White",
      "matched_product_id": "unknown",
      "match_type": "similar",
      "confidence": 0.6139144440349376
    }
  ]
}